checkrequirements/__init__.py
checkrequirements/__main__.py
checkrequirements-2023.dist-info/entry_points.txt
checkrequirements-2023.dist-info/LICENSE.md
checkrequirements-2023.dist-info/METADATA
checkrequirements-2023.dist-info/WHEEL
checkrequirements-2023.dist-info/RECORD
