Metadata-Version: 2.1
Name: checkrequirements
Version: 2023
Summary: Check that your requirements.txt is up to date with the most recent package versions
Home-page: https://github.com/FHPythonUtils/CheckRequirements
License: MIT
Author: FredHappyface
Requires-Python: >=3.8,<4.0
Classifier: Development Status :: 5 - Production/Stable
Classifier: Environment :: Console
Classifier: Environment :: MacOS X
Classifier: Environment :: Win32 (MS Windows)
Classifier: Intended Audience :: Developers
Classifier: Intended Audience :: Education
Classifier: License :: OSI Approved :: MIT License
Classifier: Natural Language :: English
Classifier: Operating System :: OS Independent
Classifier: Programming Language :: Python :: 3
Classifier: Programming Language :: Python :: 3.8
Classifier: Programming Language :: Python :: 3.9
Classifier: Programming Language :: Python :: 3.10
Classifier: Programming Language :: Python :: 3.11
Classifier: Programming Language :: Python :: Implementation :: CPython
Classifier: Topic :: Security
Classifier: Topic :: Software Development :: Libraries :: Python Modules
Classifier: Topic :: Utilities
Requires-Dist: poetry (>=1.6.1,<2)
Project-URL: Documentation, https://github.com/FHPythonUtils/CheckRequirements/blob/master/README.md
Project-URL: Repository, https://github.com/FHPythonUtils/CheckRequirements
